setup.py
dm/__init__.py
dm.zopepatches.ztest.egg-info/PKG-INFO
dm.zopepatches.ztest.egg-info/SOURCES.txt
dm.zopepatches.ztest.egg-info/dependency_links.txt
dm.zopepatches.ztest.egg-info/entry_points.txt
dm.zopepatches.ztest.egg-info/namespace_packages.txt
dm.zopepatches.ztest.egg-info/not-zip-safe
dm.zopepatches.ztest.egg-info/requires.txt
dm.zopepatches.ztest.egg-info/top_level.txt
dm/zopepatches/__init__.py
dm/zopepatches/ztest/README.txt
dm/zopepatches/ztest/VERSION.txt
dm/zopepatches/ztest/__init__.py
dm/zopepatches/ztest/test.py