Metadata-Version: 1.1
Name: dm.zopepatches.ztest
Version: 2.0.1
Summary: Script to run tests for Zope application components (without buildout).
Home-page: http://pypi.python.org/pypi/dm.zopepatches.ztest
Author: Dieter Maurer
Author-email: dieter@handshake.de
License: BSD
Keywords: script test component
Platform: UNKNOWN
Classifier: Development Status :: 5 - Production/Stable
Classifier: Intended Audience :: Developers
Classifier: License :: OSI Approved :: BSD License
Classifier: Framework :: Zope2
Classifier: Operating System :: OS Independent
Classifier: Programming Language :: Python
Classifier: Programming Language :: Python :: 2.7
Classifier: Programming Language :: Python :: 3
Classifier: Topic :: Utilities
